{
  "images": [
    {
      "enddate": "20200630",
      "url": "/th?id=OHR.BojoRiver_ZH-CN5454106636_UHD.jpg&rf=LaDigue_UHD.jpg&pid=hp&w=1920&h=1080&rs=1&c=4",
      "urlbase": "/th?id=OHR.BojoRiver_ZH-CN5454106636",
      "copyright": "Bojo河，菲律宾宿务 (© Amazing Aerial Agency/Offset by Shutterstock)",
      "copyrightlink": "",
      "title": "Bojo河"
    },
    {
      "enddate": "20200629",
      "url": "/th?id=OHR.ArganGoats_ZH-CN5346845518_UHD.jpg&rf=LaDigue_UHD.jpg&pid=hp&w=1920&h=1080&rs=1&c=4",
      "urlbase": "/th?id=OHR.ArganGoats_ZH-CN5346845518",
      "copyright": "索维拉附近摩洛哥坚果树上的山羊，摩洛哥 (© Nizz/Shutterstock)",
      "copyrightlink": "",
      "title": "索维拉附近摩洛哥坚果树上的山羊"
    },
    {
      "enddate": "20200628",
      "url": "/th?id=OHR.FoggyCastle_ROW0108897542_UHD.jpg&rf=LaDigue_UHD.jpg&pid=hp&w=1920&h=1080&rs=1&c=4",
      "urlbase": "/th?id=OHR.FoggyCastle_ROW0108897542",
      "copyright": "Chateau de Castelnaud in Perigord, France (© Peter Adams/Offset by Shutterstock)",
      "copyrightlink": "",
      "title": "Chateau de Castelnaud in Perigord, France"
    },
    {
      "enddate": "20200627",
      "url": "/th?id=OHR.MtBaldoSantuario_ZH-CN2301293454_UHD.jpg&rf=LaDigue_UHD.jpg&pid=hp&w=1920&h=1080&rs=1&c=4",
      "urlbase": "/th?id=OHR.MtBaldoSantuario_ZH-CN2301293454",
      "copyright": "Madonna della Corona教堂，意大利 (© Volodymyr Kalyniuk/Alamy)",
      "copyrightlink": "",
      "title": "Madonna della Corona教堂"
    },
    {
      "enddate": "20200626",
      "url": "/th?id=OHR.AdansoniaGrandidieri_ZH-CN1154912052_UHD.jpg&rf=LaDigue_UHD.jpg&pid=hp&w=1920&h=1080&rs=1&c=4",
      "urlbase": "/th?id=OHR.AdansoniaGrandidieri_ZH-CN1154912052",
      "copyright": "穆龙达瓦附近的格兰迪尔猴面包树林，马达加斯加 (© Thomas Marent/Minden Pictures)",
      "copyrightlink": "",
      "title": "穆龙达瓦附近的格兰迪尔猴面包树林"
    },
    {
      "enddate": "20200625",
      "url": "/th?id=OHR.duanwu2020_ZH-CN0965379603_UHD.jpg&rf=LaDigue_UHD.jpg&pid=hp&w=1920&h=1080&rs=1&c=4",
      "urlbase": "/th?id=OHR.duanwu2020_ZH-CN0965379603",
      "copyright": "【今日端午】 (© su_pei/iStock/Getty Images Plus)",
      "copyrightlink": "",
      "title": "【今日端午】"
    },
    {
      "enddate": "20200624",
      "url": "/th?id=OHR.RhodesIsland_ZH-CN0674840850_UHD.jpg&rf=LaDigue_UHD.jpg&pid=hp&w=1920&h=1080&rs=1&c=4",
      "urlbase": "/th?id=OHR.RhodesIsland_ZH-CN0674840850",
      "copyright": "鸟瞰希腊罗德岛岩石海岸上蓝白相间的遮阳伞 (© Amazing Aerial Agency/Offset by Shutterstock)",
      "copyrightlink": "",
      "title": "鸟瞰希腊罗德岛岩石海岸上蓝白相间的遮阳伞"
    },
    {
      "enddate": "20200623",
      "url": "/th?id=OHR.BullPoint_ZH-CN0520993795_UHD.jpg&rf=LaDigue_UHD.jpg&pid=hp&w=1920&h=1080&rs=1&c=4",
      "urlbase": "/th?id=OHR.BullPoint_ZH-CN0520993795",
      "copyright": "公牛角，英国德文郡 (© Robert Harding World Imagery/Offset by Shutterstock)",
      "copyrightlink": "",
      "title": "公牛角"
    },
    {
      "enddate": "20200622",
      "url": "/th?id=OHR.SouthernSunbird_ZH-CN0426670987_UHD.jpg&rf=LaDigue_UHD.jpg&pid=hp&w=1920&h=1080&rs=1&c=4",
      "urlbase": "/th?id=OHR.SouthernSunbird_ZH-CN0426670987",
      "copyright": "伯斯国家植物园针垫花上的一只雄性南方双领太阳鸟，南非开普敦 (© Martin Willis/Minden Pictures)",
      "copyrightlink": "",
      "title": "伯斯国家植物园针垫花上的一只雄性南方双领太阳鸟"
    },
    {
      "enddate": "20200621",
      "url": "/th?id=OHR.BeardedTamarin_ZH-CN0250190365_UHD.jpg&rf=LaDigue_UHD.jpg&pid=hp&w=1920&h=1080&rs=1&c=4",
      "urlbase": "/th?id=OHR.BeardedTamarin_ZH-CN0250190365",
      "copyright": "一只带着幼崽的长胡子皇狨猴 (© Chris White/iStock/Getty Images Plus)",
      "copyrightlink": "",
      "title": "一只带着幼崽的长胡子皇狨猴"
    },
    {
      "enddate": "20200620",
      "url": "/th?id=OHR.HuntingCat_ZH-CN6596392185_UHD.jpg&rf=LaDigue_UHD.jpg&pid=hp&w=1920&h=1080&rs=1&c=4",
      "urlbase": "/th?id=OHR.HuntingCat_ZH-CN6596392185",
      "copyright": "正在捕猎的丛林猫，印度 (© Lila/Alamy)",
      "copyrightlink": "",
      "title": "正在捕猎的丛林猫"
    },
    {
      "enddate": "20200619",
      "url": "/th?id=OHR.MidsummerEve_ZH-CN9981851207_UHD.jpg&rf=LaDigue_UHD.jpg&pid=hp&w=1920&h=1080&rs=1&c=4",
      "urlbase": "/th?id=OHR.MidsummerEve_ZH-CN9981851207",
      "copyright": "厄勒布鲁附近湖上的仲夏之光，瑞典 (© Anders Jorulf/Getty Images)",
      "copyrightlink": "",
      "title": "厄勒布鲁附近湖上的仲夏之光"
    },
    {
      "enddate": "20200618",
      "url": "/th?id=OHR.JabiruStork_ZH-CN0218761234_UHD.jpg&rf=LaDigue_UHD.jpg&pid=hp&w=1920&h=1080&rs=1&c=4",
      "urlbase": "/th?id=OHR.JabiruStork_ZH-CN0218761234",
      "copyright": "潘塔纳尔湿地中的裸颈鹳，巴西 (© Juan-Carlos Munoz/Minden Pictures)",
      "copyrightlink": "",
      "title": "潘塔纳尔湿地中的裸颈鹳"
    },
    {
      "enddate": "20200617",
      "url": "/th?id=OHR.Havasupai_ZH-CN0016003195_UHD.jpg&rf=LaDigue_UHD.jpg&pid=hp&w=1920&h=1080&rs=1&c=4",
      "urlbase": "/th?id=OHR.Havasupai_ZH-CN0016003195",
      "copyright": "大峡谷哈瓦苏溪上的海狸瀑布，亚利桑那州 (© Edwin Verin/Alamy)",
      "copyrightlink": "",
      "title": "大峡谷哈瓦苏溪上的海狸瀑布"
    },
    {
      "enddate": "20200616",
      "url": "/th?id=OHR.StStephens_ZH-CN9373191410_UHD.jpg&rf=LaDigue_UHD.jpg&pid=hp&w=1920&h=1080&rs=1&c=4",
      "urlbase": "/th?id=OHR.StStephens_ZH-CN9373191410",
      "copyright": "都柏林的圣斯蒂芬绿地，爱尔兰 (© L_E/Shutterstock)",
      "copyrightlink": "",
      "title": "都柏林的圣斯蒂芬绿地"
    },
    {
      "enddate": "20200615",
      "url": "/th?id=OHR.SurfSeason_ZH-CN9212464908_UHD.jpg&rf=LaDigue_UHD.jpg&pid=hp&w=1920&h=1080&rs=1&c=4",
      "urlbase": "/th?id=OHR.SurfSeason_ZH-CN9212464908",
      "copyright": "梅德威海滩棕榈树间散步的冲浪者，印尼巴厘岛 (© helivideo/GettyImages)",
      "copyrightlink": "",
      "title": "梅德威海滩棕榈树间散步的冲浪者"
    },
    {
      "enddate": "20200614",
      "url": "/th?id=OHR.WildflowersBC_ZH-CN8732388724_UHD.jpg&rf=LaDigue_UHD.jpg&pid=hp&w=1920&h=1080&rs=1&c=4",
      "urlbase": "/th?id=OHR.WildflowersBC_ZH-CN8732388724",
      "copyright": "火灾烧毁大部分森林后，野花遍地的凯尔特河野营地 (© Debra Brash/plainpicture)",
      "copyrightlink": "",
      "title": "火灾烧毁大部分森林后"
    },
    {
      "enddate": "20200613",
      "url": "/th?id=OHR.GrandsCausses_ZH-CN8463022683_UHD.jpg&rf=LaDigue_UHD.jpg&pid=hp&w=1920&h=1080&rs=1&c=4",
      "urlbase": "/th?id=OHR.GrandsCausses_ZH-CN8463022683",
      "copyright": "杜尔比河峡谷中的Moulin de Corp和小桥，法国Grands Causses自然公园 (© Hemis/Alamy)",
      "copyrightlink": "",
      "title": "杜尔比河峡谷中的Moulin de Corp和小桥"
    },
    {
      "enddate": "20200612",
      "url": "/th?id=OHR.SantaElena_ZH-CN8036210800_UHD.jpg&rf=LaDigue_UHD.jpg&pid=hp&w=1920&h=1080&rs=1&c=4",
      "urlbase": "/th?id=OHR.SantaElena_ZH-CN8036210800",
      "copyright": "银河下的圣埃伦娜峡谷，德克萨斯州大弯国家公园 (© Stanley Ford/Shutterstock)",
      "copyrightlink": "",
      "title": "银河下的圣埃伦娜峡谷"
    },
    {
      "enddate": "20200611",
      "url": "/th?id=OHR.GriboyedovCanal_ZH-CN7887366015_UHD.jpg&rf=LaDigue_UHD.jpg&pid=hp&w=1920&h=1080&rs=1&c=4",
      "urlbase": "/th?id=OHR.GriboyedovCanal_ZH-CN7887366015",
      "copyright": "格里博耶多夫运河和滴血救世主教堂，俄罗斯圣彼得堡 (© Tomas Sereda/Getty Images)",
      "copyrightlink": "",
      "title": "格里博耶多夫运河和滴血救世主教堂"
    },
    {
      "enddate": "20200610",
      "url": "/th?id=OHR.WobblyBridge_ZH-CN7751845685_UHD.jpg&rf=LaDigue_UHD.jpg&pid=hp&w=1920&h=1080&rs=1&c=4",
      "urlbase": "/th?id=OHR.WobblyBridge_ZH-CN7751845685",
      "copyright": "以圣保罗大教堂为背景的千禧桥，英国伦敦 (© Scott Baldock/Getty Images)",
      "copyrightlink": "",
      "title": "以圣保罗大教堂为背景的千禧桥"
    },
    {
      "enddate": "20200609",
      "url": "/th?id=OHR.BaronLakes_ZH-CN7541190370_UHD.jpg&rf=LaDigue_UHD.jpg&pid=hp&w=1920&h=1080&rs=1&c=4",
      "urlbase": "/th?id=OHR.BaronLakes_ZH-CN7541190370",
      "copyright": "锯齿原野中的Baron湖，爱达荷州 (© Patrick Brandenburg/Tandem Stills + Motion)",
      "copyrightlink": "",
      "title": "锯齿原野中的Baron湖"
    },
    {
      "enddate": "20200608",
      "url": "/th?id=OHR.LionSurfing_ZH-CN7369892268_UHD.jpg&rf=LaDigue_UHD.jpg&pid=hp&w=1920&h=1080&rs=1&c=4",
      "urlbase": "/th?id=OHR.LionSurfing_ZH-CN7369892268",
      "copyright": "费尔南迪纳岛海岸的加拉帕戈斯海狮，厄瓜多尔科隆群岛 (© Tui De Roy/Minden Pictures)",
      "copyrightlink": "",
      "title": "费尔南迪纳岛海岸的加拉帕戈斯海狮"
    },
    {
      "enddate": "20200607",
      "url": "/th?id=OHR.LaPertusa_ZH-CN7227946330_UHD.jpg&rf=LaDigue_UHD.jpg&pid=hp&w=1920&h=1080&rs=1&c=4",
      "urlbase": "/th?id=OHR.LaPertusa_ZH-CN7227946330",
      "copyright": "La Pertusa教堂，西班牙莱里达 (© bbsferrari/Getty Images)",
      "copyrightlink": "",
      "title": "La Pertusa教堂"
    },
    {
      "enddate": "20200606",
      "url": "/th?id=OHR.WaltersWiggles_ZH-CN6928617440_UHD.jpg&rf=LaDigue_UHD.jpg&pid=hp&w=1920&h=1080&rs=1&c=4",
      "urlbase": "/th?id=OHR.WaltersWiggles_ZH-CN6928617440",
      "copyright": "锡安国家公园中的Walter's Wiggles小径，犹他州 (© Dennis Frates/Alamy)",
      "copyrightlink": "",
      "title": "锡安国家公园中的Walter's Wiggles小径"
    },
    {
      "enddate": "20200605",
      "url": "/th?id=OHR.SynchronousFireflies_ZH-CN6323931412_UHD.jpg&rf=LaDigue_UHD.jpg&pid=hp&w=1920&h=1080&rs=1&c=4",
      "urlbase": "/th?id=OHR.SynchronousFireflies_ZH-CN6323931412",
      "copyright": "同步发光萤火虫照亮了大烟山国家公园中的森林 (© Floris van Breugel/Minden Pictures)",
      "copyrightlink": "",
      "title": "同步发光萤火虫照亮了大烟山国家公园中的森林"
    },
    {
      "enddate": "20200604",
      "url": "/th?id=OHR.PontFawr_ZH-CN1780190468_UHD.jpg&rf=LaDigue_UHD.jpg&pid=hp&w=1920&h=1080&rs=1&c=4",
      "urlbase": "/th?id=OHR.PontFawr_ZH-CN1780190468",
      "copyright": "兰鲁斯特一座名为Pont Fawr的石拱桥，英国威尔士 (© Pajor Pawel/Shutterstock)",
      "copyrightlink": "",
      "title": "兰鲁斯特一座名为Pont Fawr的石拱桥"
    },
    {
      "enddate": "20200603",
      "url": "/th?id=OHR.WhiteRimTrail_ZH-CN1574735777_UHD.jpg&rf=LaDigue_UHD.jpg&pid=hp&w=1920&h=1080&rs=1&c=4",
      "urlbase": "/th?id=OHR.WhiteRimTrail_ZH-CN1574735777",
      "copyright": "两名山地车骑手在白缘公路上沿着谢福小道的转弯处骑行 ，犹他州峡谷地国家公园 (© Grant Ordelheide/Tandem Stills + Motion)",
      "copyrightlink": "",
      "title": "两名山地车骑手在白缘公路上沿着谢福小道的转弯处骑行"
    },
    {
      "enddate": "20200602",
      "url": "/th?id=OHR.JasperSunwaptaVideo_ZH-CN1403296497_UHD.jpg&rf=LaDigue_UHD.jpg&pid=hp&w=1920&h=1080&rs=1&c=4",
      "urlbase": "/th?id=OHR.JasperSunwaptaVideo_ZH-CN1403296497",
      "copyright": "辛华达瀑布，加拿大贾斯珀国家公园 (© Schroptschop/Getty Images)",
      "copyrightlink": "",
      "title": "辛华达瀑布"
    },
    {
      "enddate": "20200601",
      "url": "/th?id=OHR.GreatReefDay_ZH-CN1185297376_UHD.jpg&rf=LaDigue_UHD.jpg&pid=hp&w=1920&h=1080&rs=1&c=4",
      "urlbase": "/th?id=OHR.GreatReefDay_ZH-CN1185297376",
      "copyright": "大堡礁，澳大利亚昆士兰 (© AWL Images/Danita Delimont)",
      "copyrightlink": "",
      "title": "大堡礁"
    }
  ]
}
