{
  "images": [
    {
      "enddate": "20170731",
      "url": "https://cdn.bimg.cc/bing/2017/OHR.Mellieha_EN-AU9931288836_1920x1080.jpg",
      "urlbase": "/th?id=OHR.Mellieha_EN-AU9931288836",
      "copyright": "梅利哈俯视视图，马耳他 (© Zoltan Gabor/Alamy)",
      "copyrightlink": "",
      "title": "梅利哈俯视视图"
    },
    {
      "enddate": "20170730",
      "url": "https://cdn.bimg.cc/bing/2017/OHR.MineralCliffs_EN-AU10636449444_1920x1080.jpg",
      "urlbase": "/th?id=OHR.MineralCliffs_EN-AU10636449444",
      "copyright": "画岩湖滨，美国密歇根州 (© Steve Gettle/Minden Pictures)",
      "copyrightlink": "",
      "title": "画岩湖滨"
    },
    {
      "enddate": "20170729",
      "url": "https://cdn.bimg.cc/bing/2017/OHR.WaSqPk_EN-AU9813692413_1920x1080.jpg",
      "urlbase": "/th?id=OHR.WaSqPk_EN-AU9813692413",
      "copyright": "华盛顿广场公园鸟瞰图，美国纽约 (© New York on Air/Offset)",
      "copyrightlink": "",
      "title": "华盛顿广场公园鸟瞰图"
    },
    {
      "enddate": "20170728",
      "url": "https://cdn.bimg.cc/bing/2017/OHR.TempleStreet_ZH-CN7471755280_1920x1080.jpg",
      "urlbase": "/th?id=OHR.TempleStreet_ZH-CN7471755280",
      "copyright": "香港油麻地庙街夜市 (© Peter Stewart/500px)",
      "copyrightlink": "",
      "title": "香港油麻地庙街夜市"
    },
    {
      "enddate": "20170727",
      "url": "https://cdn.bimg.cc/bing/2017/OHR.HuangshanClouds_EN-AU10777890471_1920x1080.jpg",
      "urlbase": "/th?id=OHR.HuangshanClouds_EN-AU10777890471",
      "copyright": "黄山，中国安徽省 (© Oktay Ortakcioglu/Getty Images)",
      "copyrightlink": "",
      "title": "黄山"
    },
    {
      "enddate": "20170726",
      "url": "https://cdn.bimg.cc/bing/2017/OHR.WilsonPeakWindow_EN-AU10136791556_1920x1080.jpg",
      "urlbase": "/th?id=OHR.WilsonPeakWindow_EN-AU10136791556",
      "copyright": "从鬼城Alta看到的威尔逊峰，美国科罗拉多州 (© Grant Ordelheide/Tandem Stills + Motion)",
      "copyrightlink": "",
      "title": "从鬼城Alta看到的威尔逊峰"
    },
    {
      "enddate": "20170725",
      "url": "https://cdn.bimg.cc/bing/2017/OHR.ReinebringenRidge_EN-AU10023256564_1920x1080.jpg",
      "urlbase": "/th?id=OHR.ReinebringenRidge_EN-AU10023256564",
      "copyright": "莫斯克内斯岛雷讷村雷纳布林根山岭的景观，挪威 (© David Varga/Shutterstock)",
      "copyrightlink": "",
      "title": "莫斯克内斯岛雷讷村雷纳布林根山岭的景观"
    },
    {
      "enddate": "20170724",
      "url": "https://cdn.bimg.cc/bing/2017/OHR.RainbowLorikeets_EN-AU9196763566_1920x1080.jpg",
      "urlbase": "/th?id=OHR.RainbowLorikeets_EN-AU9196763566",
      "copyright": "虹彩吸蜜鹦鹉，澳大利亚威勒比  (© Roger Powell/Minden Pictures)",
      "copyrightlink": "",
      "title": "虹彩吸蜜鹦鹉"
    },
    {
      "enddate": "20170723",
      "url": "https://cdn.bimg.cc/bing/2017/OHR.LosMonegros_EN-AU13545190344_1920x1080.jpg",
      "urlbase": "/th?id=OHR.LosMonegros_EN-AU13545190344",
      "copyright": "洛斯莫内格罗斯附近的洛斯莫内格罗斯沙漠农业区，西班牙 (© Juan Carlos Mu?oz/age fotostock)",
      "copyrightlink": "",
      "title": "洛斯莫内格罗斯附近的洛斯莫内格罗斯沙漠农业区"
    },
    {
      "enddate": "20170722",
      "url": "https://cdn.bimg.cc/bing/2017/OHR.Econlockhatchee_EN-AU9702194142_1920x1080.jpg",
      "urlbase": "/th?id=OHR.Econlockhatchee_EN-AU9702194142",
      "copyright": "【今日大暑】Econlockhatchee 河上的吊床露营，美国佛罗里达州 (© Mac Stone/Tandem Stills + Motion)",
      "copyrightlink": "",
      "title": "【今日大暑】Econlockhatchee 河上的吊床露营"
    },
    {
      "enddate": "20170721",
      "url": "https://cdn.bimg.cc/bing/2017/OHR.EborFallsVideo_EN-AU8428374700_1920x1080.jpg",
      "urlbase": "/th?id=OHR.EborFallsVideo_EN-AU8428374700",
      "copyright": "Guy Fawkes River国家公园内的埃博瀑布，澳大利亚 (© Ingo Oeland/Alamy)",
      "copyrightlink": "",
      "title": "Guy Fawkes River国家公园内的埃博瀑布"
    },
    {
      "enddate": "20170720",
      "url": "https://cdn.bimg.cc/bing/2017/OHR.GlastonburyMoon_EN-AU10251307154_1920x1080.jpg",
      "urlbase": "/th?id=OHR.GlastonburyMoon_EN-AU10251307154",
      "copyright": "格拉斯顿伯里高冈上方升起的月亮，英国 (© Matt Cardy/Getty Images)",
      "copyrightlink": "",
      "title": "格拉斯顿伯里高冈上方升起的月亮"
    },
    {
      "enddate": "20170719",
      "url": "https://cdn.bimg.cc/bing/2017/OHR.Aldabra_EN-AU10067035056_1920x1080.jpg",
      "urlbase": "/th?id=OHR.Aldabra_EN-AU10067035056",
      "copyright": "印度洋上的阿尔达布拉群岛 (© Wil Meinderts/Minden Pictures)",
      "copyrightlink": "",
      "title": "印度洋上的阿尔达布拉群岛"
    },
    {
      "enddate": "20170718",
      "url": "https://cdn.bimg.cc/bing/2017/OHR.GeladaSimien_EN-AU7386132793_1920x1080.jpg",
      "urlbase": "/th?id=OHR.GeladaSimien_EN-AU7386132793",
      "copyright": "塞米恩国家公园内的狮尾狒， 埃塞俄比亚 (© Thomas Marent/Minden Pictures)",
      "copyrightlink": "",
      "title": "塞米恩国家公园内的狮尾狒"
    },
    {
      "enddate": "20170717",
      "url": "https://cdn.bimg.cc/bing/2017/OHR.CrescentCityConnection_EN-AU11247361628_1920x1080.jpg",
      "urlbase": "/th?id=OHR.CrescentCityConnection_EN-AU11247361628",
      "copyright": "新奥尔良市的新月城大桥，美国路易斯安那州 (© Fred Gramoso/500px)",
      "copyrightlink": "",
      "title": "新奥尔良市的新月城大桥"
    },
    {
      "enddate": "20170716",
      "url": "https://cdn.bimg.cc/bing/2017/OHR.FelgueirasLighthouse_EN-AU11198579022_1920x1080.jpg",
      "urlbase": "/th?id=OHR.FelgueirasLighthouse_EN-AU11198579022",
      "copyright": "波尔图一个名叫费尔盖拉什的灯塔， 葡萄牙 (© Veselin Malinov/500px)",
      "copyrightlink": "",
      "title": "波尔图一个名叫费尔盖拉什的灯塔"
    },
    {
      "enddate": "20170715",
      "url": "https://cdn.bimg.cc/bing/2017/OHR.ColorfulSalt_EN-AU13586718897_1920x1080.jpg",
      "urlbase": "/th?id=OHR.ColorfulSalt_EN-AU13586718897",
      "copyright": "旧金山湾的盐蒸发池，美国加利福尼亚州 (© Jason Hawkes/REX/Shutterstock)",
      "copyrightlink": "",
      "title": "旧金山湾的盐蒸发池"
    },
    {
      "enddate": "20170714",
      "url": "https://cdn.bimg.cc/bing/2017/OHR.TuileriesGardenWheel_EN-AU11916079727_1920x1080.jpg",
      "urlbase": "/th?id=OHR.TuileriesGardenWheel_EN-AU11916079727",
      "copyright": "杜乐丽花园内的摩天轮，法国巴黎 (© Tardy Herv/Getty Images)",
      "copyrightlink": "",
      "title": "杜乐丽花园内的摩天轮"
    },
    {
      "enddate": "20170713",
      "url": "https://cdn.bimg.cc/bing/2017/OHR.LagazuoiRefuge_EN-AU12120955316_1920x1080.jpg",
      "urlbase": "/th?id=OHR.LagazuoiRefuge_EN-AU12120955316",
      "copyright": "从科尔蒂纳丹佩佐市附近的Lagazuoi山观看佩尔莫山，意大利 (© Olimpio Fantuz/Offset)",
      "copyrightlink": "",
      "title": "从科尔蒂纳丹佩佐市附近的Lagazuoi山观看佩尔莫山"
    },
    {
      "enddate": "20170712",
      "url": "https://cdn.bimg.cc/bing/2017/OHR.GhostCrab_EN-AU12586461381_1920x1080.jpg",
      "urlbase": "/th?id=OHR.GhostCrab_EN-AU12586461381",
      "copyright": "大西洋鬼蟹 (© Luciano Candisani/Minden Pictures)",
      "copyrightlink": "",
      "title": "大西洋鬼蟹"
    },
    {
      "enddate": "20170711",
      "url": "https://cdn.bimg.cc/bing/2017/OHR.MartapuraMarket_EN-AU9502204987_1920x1080.jpg",
      "urlbase": "/th?id=OHR.MartapuraMarket_EN-AU9502204987",
      "copyright": "印尼马塔普拉河上的Lok Baintan水上市场 (© Fauzan Mauddin/Solent News/REX/Shutterstock)",
      "copyrightlink": "",
      "title": "印尼马塔普拉河上的Lok Baintan水上市场"
    },
    {
      "enddate": "20170710",
      "url": "https://cdn.bimg.cc/bing/2017/OHR.DerbyshireSheep_EN-AU8298134447_1920x1080.jpg",
      "urlbase": "/th?id=OHR.DerbyshireSheep_EN-AU8298134447",
      "copyright": "峰区国家公园内的绵羊，英国德比郡 (© James Mills/500px)",
      "copyrightlink": "",
      "title": "峰区国家公园内的绵羊"
    },
    {
      "enddate": "20170709",
      "url": "https://cdn.bimg.cc/bing/2017/OHR.Umbrellas_EN-AU8739718706_1920x1080.jpg",
      "urlbase": "/th?id=OHR.Umbrellas_EN-AU8739718706",
      "copyright": "马其顿当代艺术博物馆外乔治·宗古鲁普罗斯设计的“雨伞”雕塑，希腊塞萨洛尼基 (© SIAATH/Shutterstock)",
      "copyrightlink": "",
      "title": "马其顿当代艺术博物馆外乔治·宗古鲁普罗斯设计的“雨伞”雕塑"
    },
    {
      "enddate": "20170708",
      "url": "https://cdn.bimg.cc/bing/2017/OHR.CharcoAzul_EN-AU9947089589_1920x1080.jpg",
      "urlbase": "/th?id=OHR.CharcoAzul_EN-AU9947089589",
      "copyright": "耶罗岛上的洞穴，西班牙加那利群岛 (© Huber/Sime/eStock Photo)",
      "copyrightlink": "",
      "title": "耶罗岛上的洞穴"
    },
    {
      "enddate": "20170707",
      "url": "https://cdn.bimg.cc/bing/2017/OHR.Umbrella_ZH-CN8238029705_1920x1080.jpg",
      "urlbase": "/th?id=OHR.Umbrella_ZH-CN8238029705",
      "copyright": "【今日小暑】游客在枣庄市台儿庄区运河湿地公园观赏莲花，中国山东省 (Gao Qimin/Xinhua/Alamy Live News)",
      "copyrightlink": "",
      "title": "【今日小暑】游客在枣庄市台儿庄区运河湿地公园观赏莲花"
    },
    {
      "enddate": "20170706",
      "url": "https://cdn.bimg.cc/bing/2017/OHR.SnailsKissing_EN-AU7861942488_1920x1080.jpg",
      "urlbase": "/th?id=OHR.SnailsKissing_EN-AU7861942488",
      "copyright": "蜗牛之吻，印度尼西亚三发县 (© Solent News/Rex Shutterstock)",
      "copyrightlink": "",
      "title": "蜗牛之吻"
    },
    {
      "enddate": "20170705",
      "url": "https://cdn.bimg.cc/bing/2017/OHR.RestArea_EN-AU12659313216_1920x1080.jpg",
      "urlbase": "/th?id=OHR.RestArea_EN-AU12659313216",
      "copyright": "白沙国家纪念碑，美国新墨西哥州 (© Peter Burgstaller/Gallery Stock)",
      "copyrightlink": "",
      "title": "白沙国家纪念碑"
    },
    {
      "enddate": "20170704",
      "url": "https://cdn.bimg.cc/bing/2017/OHR.SonnenblumeHummel_EN-AU13411467664_1920x1080.jpg",
      "urlbase": "/th?id=OHR.SonnenblumeHummel_EN-AU13411467664",
      "copyright": "一只大黄蜂在菲希塔市附近的巴伐利亚森林中的向日葵上，德国巴伐利亚 (© Rüdiger Hess/geo-select FotoArt)",
      "copyrightlink": "",
      "title": "一只大黄蜂在菲希塔市附近的巴伐利亚森林中的向日葵上"
    },
    {
      "enddate": "20170703",
      "url": "https://cdn.bimg.cc/bing/2017/OHR.LongTailedBushtits_EN-AU9123255134_1920x1080.jpg",
      "urlbase": "/th?id=OHR.LongTailedBushtits_EN-AU9123255134",
      "copyright": "银喉长尾山雀，德国埃尔丁 (© H. Schmidbauer/Offset)",
      "copyrightlink": "",
      "title": "银喉长尾山雀"
    },
    {
      "enddate": "20170702",
      "url": "https://cdn.bimg.cc/bing/2017/OHR.ConeyIslandAerial_EN-AU8660420119_1920x1080.jpg",
      "urlbase": "/th?id=OHR.ConeyIslandAerial_EN-AU8660420119",
      "copyright": "科尼岛上的游乐场设施，美国纽约  (© New York on Air/Offset)",
      "copyrightlink": "",
      "title": "科尼岛上的游乐场设施"
    },
    {
      "enddate": "20170701",
      "url": "https://cdn.bimg.cc/bing/2017/OHR.SunwaptaFalls_JA-JP9240176817_1920x1080.jpg",
      "urlbase": "/th?id=OHR.SunwaptaFalls_JA-JP9240176817",
      "copyright": "贾斯珀国家公园内的辛华达瀑布，加拿大艾伯塔省 (© Mana Arabi/Shutterstock)",
      "copyrightlink": "",
      "title": "贾斯珀国家公园内的辛华达瀑布"
    }
  ]
}
